abara_file_io/__init__.py
abara_file_io/common_io_wrapper.py
abara_file_io/ini.py
abara_file_io/json.py
abara_file_io/py.typed
abara_file_io/text.py
abara_file_io/toml.py
abara_file_io/yaml.py
abara_file_io-1.0.1.dist-info/METADATA
abara_file_io-1.0.1.dist-info/WHEEL
abara_file_io-1.0.1.dist-info/licenses/LICENSE
abara_file_io-1.0.1.dist-info/RECORD
