Metadata-Version: 2.4
Name: abara-file-io
Version: 1.0.1
Summary: This is a library that reads and writes Python local files in the most efficient way possible, without the need for detailed configuration.
Author-email: abara <abarabakuhatsu@gmail.com>
License-File: LICENSE
Requires-Python: >=3.12
Requires-Dist: charset-normalizer>=3.4.2
Requires-Dist: ruamel-yaml>=0.18.10
Requires-Dist: tomli-w>=1.2.0
